{
	"configurations" : 
	[
		{
			"directories" : 
			[
				{
					"build" : ".",
					"jsonFile" : "directory-.-Debug-f5ebdc15457944623624.json",
					"minimumCMakeVersion" : 
					{
						"string" : "3.8"
					},
					"projectIndex" : 0,
					"source" : ".",
					"targetIndexes" : 
					[
						0
					]
				}
			],
			"name" : "Debug",
			"projects" : 
			[
				{
					"directoryIndexes" : 
					[
						0
					],
					"name" : "minihell",
					"targetIndexes" : 
					[
						0
					]
				}
			],
			"targets" : 
			[
				{
					"directoryIndex" : 0,
					"id" : "inputsim::@6890427a1f51a3e7e1df",
					"jsonFile" : "target-inputsim-Debug-c49d925001f6ed6440fd.json",
					"name" : "inputsim",
					"projectIndex" : 0
				}
			]
		}
	],
	"kind" : "codemodel",
	"paths" : 
	{
		"build" : "/home/hayden/Documents/GitHub_Repos/cs415.coble/asg03/build",
		"source" : "/home/hayden/Documents/GitHub_Repos/cs415.coble/asg03"
	},
	"version" : 
	{
		"major" : 2,
		"minor" : 3
	}
}
